{"cameraMode":{"drawMode":0,"name":"Shaded","section":"Shading Mode"},"sceneLighting":true,"audioPlay":false,"sceneViewState":{"showFog":true,"showMaterialUpdate":false,"showSkybox":true,"showFlares":true,"showImageEffects":true,"showParticleSystems":true},"in2DMode":false,"pivot":{"x":-0.6816918253898621,"y":2.7438621520996095,"z":6.797160625457764},"rotation":{"x":0.02580985240638256,"y":-0.003005359787493944,"z":0.00008807828999124467,"w":0.9997133612632752},"size":6.959001064300537,"orthographic":false}